wapordl/__init__.py
wapordl/bounding_boxes.py
wapordl/main.py
wapordl/overview_selector.py
wapordl/region_selector.py
wapordl/unit_convertor.py
wapordl/variable_descriptions.py
wapordl/__pycache__/__init__.cpython-312.pyc
wapordl/products/__init__.py
wapordl/products/agera5.py
wapordl/products/wapor3.py
wapordl/toolbox/__init__.py
wapordl/toolbox/ogr_gdal.py
wapordl/toolbox/query.py
wapordl/toolbox/ts_queries.py
wapordl-1.2.1.dist-info/licenses/LICENSE
wapordl-1.2.1.dist-info/METADATA
wapordl-1.2.1.dist-info/WHEEL
wapordl-1.2.1.dist-info/top_level.txt
wapordl-1.2.1.dist-info/RECORD
